wagtailmautic/__init__.py
wagtailmautic/admin.py
wagtailmautic/api.py
wagtailmautic/apps.py
wagtailmautic/errors.py
wagtailmautic/fields.py
wagtailmautic/forms.py
wagtailmautic/models.py
wagtailmautic/tests.py
wagtailmautic/utils.py
wagtailmautic/views.py
wagtailmautic/migrations/0001_initial.py
wagtailmautic/migrations/__init__.py
wagtailmautic/templates/form_thank_you_landing.html
wagtail_mautic_integration-0.0.1.dist-info/LICENSE
wagtail_mautic_integration-0.0.1.dist-info/METADATA
wagtail_mautic_integration-0.0.1.dist-info/WHEEL
wagtail_mautic_integration-0.0.1.dist-info/top_level.txt
wagtail_mautic_integration-0.0.1.dist-info/RECORD
