Metadata-Version: 2.1
Name: wagtail-mautic-integration
Version: 0.0.1
Summary: Integration of Mautic Email Marketing in Wagtail Projects.
Home-page: https://github.com/wmo-raf/wagtail-mautic-integration
Author: Erick Otenyo
Author-email: otenyo.erick@gmail.com
License: MIT
Classifier: Development Status :: 4 - Beta
Classifier: Environment :: Web Environment
Classifier: Intended Audience :: Developers
Classifier: License :: OSI Approved :: MIT License
Classifier: Operating System :: OS Independent
Classifier: Programming Language :: Python :: 3 :: Only
Classifier: Programming Language :: Python :: 3.9
Classifier: Programming Language :: Python :: Implementation :: CPython
Classifier: Topic :: Software Development :: Libraries :: Application Frameworks
Classifier: Topic :: Software Development :: Libraries :: Python Modules
Requires-Python: >=3.9
License-File: LICENSE
Requires-Dist: wagtail (>=4.2.2)
Requires-Dist: requests-oauthlib (>=1.3.1)
